<included>

	<logger name="org.apache" level="warn"/>
	<logger name="org.springframework" level="warn"/>
	<logger name="org.springframework.transaction" level="warn"/>
	
	<logger name="play" level="info"/>
	<logger name="application" level="info"/>
	<logger name="be.objectify" level="warn"/>
	<logger name="java.sql" level="warn"/>
	<logger name="com.avaje.ebean" level="warn"/>
	<logger name="com.jolbox" level="warn"/>
	
	<logger name="com.avaje.ebean.config.PropertyMapLoader" level="OFF" />
	<logger name="com.avaje.ebeaninternal.server.core.XmlConfigLoader" level="OFF" />
	<logger name="com.avaje.ebeaninternal.server.lib.BackgroundThread" level="OFF" />
	<logger name="com.gargoylesoftware.htmlunit.javascript" level="OFF" />

	<logger name="ScholasticDonationsLogger" level="debug" additivity="false">
		<appender-ref ref="ScholasticDonations"/>   
	</logger>
	<logger name="ScholasticReceiptsLogger" level="debug" additivity="false">
		<appender-ref ref="ScholasticReceipts"/>   
	</logger>

	<root level="info">
		<appender-ref ref="stdout" />
		<appender-ref ref="ScholasticWebApplication" />
	</root>
</included>